{
  "X": [
    [24, 69, 70, 205, 11],
    [4, 46, 70, 69, 6],
    [10, 36, 39, 134, 4],
    [6, 22, 30, 104, 3],
    [32, 164, 272, 437, 40],
    [3, 53, 49, 111, 8],
    [20, 47, 33, 201, 8],
    [8, 13, 24, 150, 10],
    [81, 181, 188, 739, 61],
    [165, 297, 418, 1325, 102],
    [6, 31, 37, 56, 4],
    [3, 7, 25, 10, 2],
    [15, 10, 73, 100, 14],
    [5, 22, 36, 147, 3],
    [9, 49, 53, 114, 7],
    [2, 12, 13, 5, 2],
    [5, 1, 5, 0, 1],
    [3, 14, 22, 95, 2],
    [7, 14, 23, 161, 7],
    [21, 72, 218, 566, 33],
    [14, 55, 40, 269, 10],
    [73, 158, 166, 784, 51],
    [3, 18, 39, 66, 3],
    [31, 94, 225, 287, 38],
    [96, 178, 422, 666, 60],
    [50, 127, 101, 472, 12],
    [12, 48, 75, 321, 15],
    [12, 20, 56, 190, 5],
    [22, 132, 217, 366, 10],
    [13, 34, 86, 112, 5],
    [96, 179, 154, 815, 41],
    [30, 56, 60, 313, 18],
    [30, 109, 200, 268, 22],
    [1, 18, 24, 45, 0],
    [7, 47, 127, 138, 13],
    [6, 77, 126, 230, 16],
    [28, 145, 311, 381, 43],
    [13, 65, 150, 211, 13],
    [24, 129, 256, 286, 18],
    [28, 119, 297, 395, 36],
    [10, 39, 110, 288, 12],
    [30, 78, 150, 256, 32],
    [116, 282, 415, 576, 83],
    [37, 122, 190, 260, 32],
    [66, 172, 284, 522, 31],
    [11, 79, 64, 137, 6],
    [3, 10, 57, 185, 5],
    [30, 90, 39, 217, 10],
    [92, 319, 513, 1077, 59],
    [0, 19, 28, 94, 4],
    [7, 22, 33, 56, 6],
    [21, 84, 149, 355, 27],
    [11, 48, 174, 342, 21],
    [21, 87, 126, 292, 26],
    [26, 20, 122, 96, 22],
    [156, 414, 677, 1655, 96],
    [17, 80, 75, 169, 17],
    [107, 514, 396, 940, 116],
    [13, 107, 54, 203, 9]
  ],
  "W": [
    [27, 113, 159, 60, 20],
    [63, 55, 58, 10, 9],
    [26, 47, 118, 18, 14],
    [30, 26, 85, 18, 6],
    [145, 285, 351, 96, 68],
    [37, 56, 102, 15, 14],
    [25, 59, 167, 39, 19],
    [4, 30, 139, 17, 15],
    [67, 293, 625, 149, 116],
    [102, 608, 1138, 284, 175],
    [31, 38, 45, 13, 7],
    [12, 17, 8, 7, 3],
    [8, 79, 82, 24, 19],
    [5, 53, 120, 22, 13],
    [39, 63, 94, 15, 21],
    [10, 12, 2, 4, 6],
    [1, 7, 0, 2, 2],
    [5, 31, 80, 14, 6],
    [2, 38, 140, 19, 13],
    [25, 285, 467, 77, 56],
    [16, 71, 247, 38, 16],
    [50, 280, 675, 160, 67],
    [17, 39, 46, 15, 12],
    [27, 301, 231, 68, 48],
    [54, 519, 536, 187, 126],
    [61, 150, 425, 84, 42],
    [8, 126, 296, 20, 21],
    [15, 83, 142, 27, 16],
    [82, 272, 290, 61, 42],
    [32, 98, 79, 26, 15],
    [80, 231, 728, 147, 99],
    [20, 92, 271, 54, 40],
    [57, 272, 199, 66, 35],
    [19, 28, 32, 4, 5],
    [24, 148, 104, 25, 31],
    [32, 182, 165, 32, 44],
    [83, 368, 315, 75, 67],
    [45, 164, 178, 36, 29],
    [68, 309, 236, 51, 49],
    [51, 393, 314, 77, 40],
    [14, 143, 238, 40, 24],
    [42, 204, 197, 55, 48],
    [101, 607, 460, 188, 116],
    [38, 275, 206, 70, 52],
    [73, 369, 450, 118, 65],
    [29, 110, 110, 30, 18],
    [4, 51, 165, 24, 16],
    [45, 84, 190, 35, 32],
    [152, 667, 906, 205, 130],
    [27, 22, 80, 7, 9],
    [7, 49, 43, 20, 5],
    [39, 213, 293, 49, 42],
    [54, 188, 295, 35, 24],
    [50, 177, 234, 47, 44],
    [7, 148, 83, 31, 17],
    [206, 891, 1362, 307, 232],
    [30, 115, 145, 42, 26],
    [212, 693, 860, 165, 143],
    [55, 104, 190, 17, 20]
  ],
  "method": "mvn_cdf",
  "mvncdf_method": "genz",
  "mvncdf_samples": 5000,
  "mvncdf_error": 1e-06,
  "cond_prob": [
    [
      [0, 0, 0, 0, 0],
      [0, 0, 0, 0, 0],
      [0, 0, 0, 0, 0],
      [0, 0, 0, 0, 0],
      [0, 0, 0, 0, 0]
    ],
    [
      [0, 0, 0, 0, 0],
      [0, 0, 0, 0, 0],
      [0, 0, 0, 0, 0],
      [0, 0, 0, 0, 0],
      [0, 0, 0, 0, 0]
    ],
    [
      [0, 0, 0, 0, 0],
      [0, 0, 0, 0, 0],
      [0, 0, 0, 0, 0],
      [0, 0, 0, 0, 0],
      [0, 0, 0, 0, 0]
    ],
    [
      [0, 0, 0, 0, 0],
      [0, 0, 0, 0, 0],
      [0, 0, 0, 0, 0],
      [0, 0, 0, 0, 0],
      [0, 0, 0, 0, 0]
    ],
    [
      [0, 0, 0, 0, 0],
      [0, 0, 0, 0, 0],
      [0, 0, 0, 0, 0],
      [0, 0, 0, 0, 0],
      [0, 0, 0, 0, 0]
    ],
    [
      [0, 0, 0, 0, 0],
      [0, 0, 0, 0, 0],
      [0, 0, 0, 0, 0],
      [0, 0, 0, 0, 0],
      [0, 0, 0, 0, 0]
    ],
    [
      [0, 0, 0, 0, 0],
      [0, 0, 0, 0, 0],
      [0, 0, 0, 0, 0],
      [0, 0, 0, 0, 0],
      [0, 0, 0, 0, 0]
    ],
    [
      [0, 0, 0, 0, 0],
      [0, 0, 0, 0, 0],
      [0, 0, 0, 0, 0],
      [0, 0, 0, 0, 0],
      [0, 0, 0, 0, 0]
    ],
    [
      [0, 0, 0, 0, 0],
      [0, 0, 0, 0, 0],
      [0, 0, 0, 0, 0],
      [0, 0, 0, 0, 0],
      [0, 0, 0, 0, 0]
    ],
    [
      [0, 0, 0, 0, 0],
      [0, 0, 0, 0, 0],
      [0, 0, 0, 0, 0],
      [0, 0, 0, 0, 0],
      [0, 0, 0, 0, 0]
    ],
    [
      [0, 0, 0, 0, 0],
      [0, 0, 0, 0, 0],
      [0, 0, 0, 0, 0],
      [0, 0, 0, 0, 0],
      [0, 0, 0, 0, 0]
    ],
    [
      [0, 0, 0, 0, 0],
      [0, 0, 0, 0, 0],
      [0, 0, 0, 0, 0],
      [0, 0, 0, 0, 0],
      [0, 0, 0, 0, 0]
    ],
    [
      [0, 0, 0, 0, 0],
      [0, 0, 0, 0, 0],
      [0, 0, 0, 0, 0],
      [0, 0, 0, 0, 0],
      [0, 0, 0, 0, 0]
    ],
    [
      [0, 0, 0, 0, 0],
      [0, 0, 0, 0, 0],
      [0, 0, 0, 0, 0],
      [0, 0, 0, 0, 0],
      [0, 0, 0, 0, 0]
    ],
    [
      [0, 0, 0, 0, 0],
      [0, 0, 0, 0, 0],
      [0, 0, 0, 0, 0],
      [0, 0, 0, 0, 0],
      [0, 0, 0, 0, 0]
    ],
    [
      [0, 0, 0, 0, 0],
      [0, 0, 0, 0, 0],
      [0, 0, 0, 0, 0],
      [0, 0, 0, 0, 0],
      [0, 0, 0, 0, 0]
    ],
    [
      [0, 0, 0, 0, 0],
      [0, 0, 0, 0, 0],
      [0, 0, 0, 0, 0],
      [0, 0, 0, 0, 0],
      [0, 0, 0, 0, 0]
    ],
    [
      [0, 0, 0, 0, 0],
      [0, 0, 0, 0, 0],
      [0, 0, 0, 0, 0],
      [0, 0, 0, 0, 0],
      [0, 0, 0, 0, 0]
    ],
    [
      [0, 0, 0, 0, 0],
      [0, 0, 0, 0, 0],
      [0, 0, 0, 0, 0],
      [0, 0, 0, 0, 0],
      [0, 0, 0, 0, 0]
    ],
    [
      [0, 0, 0, 0, 0],
      [0, 0, 0, 0, 0],
      [0, 0, 0, 0, 0],
      [0, 0, 0, 0, 0],
      [0, 0, 0, 0, 0]
    ],
    [
      [0, 0, 0, 0, 0],
      [0, 0, 0, 0, 0],
      [0, 0, 0, 0, 0],
      [0, 0, 0, 0, 0],
      [0, 0, 0, 0, 0]
    ],
    [
      [0, 0, 0, 0, 0],
      [0, 0, 0, 0, 0],
      [0, 0, 0, 0, 0],
      [0, 0, 0, 0, 0],
      [0, 0, 0, 0, 0]
    ],
    [
      [0, 0, 0, 0, 0],
      [0, 0, 0, 0, 0],
      [0, 0, 0, 0, 0],
      [0, 0, 0, 0, 0],
      [0, 0, 0, 0, 0]
    ],
    [
      [0, 0, 0, 0, 0],
      [0, 0, 0, 0, 0],
      [0, 0, 0, 0, 0],
      [0, 0, 0, 0, 0],
      [0, 0, 0, 0, 0]
    ],
    [
      [0, 0, 0, 0, 0],
      [0, 0, 0, 0, 0],
      [0, 0, 0, 0, 0],
      [0, 0, 0, 0, 0],
      [0, 0, 0, 0, 0]
    ],
    [
      [0, 0, 0, 0, 0],
      [0, 0, 0, 0, 0],
      [0, 0, 0, 0, 0],
      [0, 0, 0, 0, 0],
      [0, 0, 0, 0, 0]
    ],
    [
      [0, 0, 0, 0, 0],
      [0, 0, 0, 0, 0],
      [0, 0, 0, 0, 0],
      [0, 0, 0, 0, 0],
      [0, 0, 0, 0, 0]
    ],
    [
      [0, 0, 0, 0, 0],
      [0, 0, 0, 0, 0],
      [0, 0, 0, 0, 0],
      [0, 0, 0, 0, 0],
      [0, 0, 0, 0, 0]
    ],
    [
      [0, 0, 0, 0, 0],
      [0, 0, 0, 0, 0],
      [0, 0, 0, 0, 0],
      [0, 0, 0, 0, 0],
      [0, 0, 0, 0, 0]
    ],
    [
      [0, 0, 0, 0, 0],
      [0, 0, 0, 0, 0],
      [0, 0, 0, 0, 0],
      [0, 0, 0, 0, 0],
      [0, 0, 0, 0, 0]
    ],
    [
      [0, 0, 0, 0, 0],
      [0, 0, 0, 0, 0],
      [0, 0, 0, 0, 0],
      [0, 0, 0, 0, 0],
      [0, 0, 0, 0, 0]
    ],
    [
      [0, 0, 0, 0, 0],
      [0, 0, 0, 0, 0],
      [0, 0, 0, 0, 0],
      [0, 0, 0, 0, 0],
      [0, 0, 0, 0, 0]
    ],
    [
      [0, 0, 0, 0, 0],
      [0, 0, 0, 0, 0],
      [0, 0, 0, 0, 0],
      [0, 0, 0, 0, 0],
      [0, 0, 0, 0, 0]
    ],
    [
      [0, 0, 0, 0, 0],
      [0, 0, 0, 0, 0],
      [0, 0, 0, 0, 0],
      [0, 0, 0, 0, 0],
      [0, 0, 0, 0, 0]
    ],
    [
      [0, 0, 0, 0, 0],
      [0, 0, 0, 0, 0],
      [0, 0, 0, 0, 0],
      [0, 0, 0, 0, 0],
      [0, 0, 0, 0, 0]
    ],
    [
      [0, 0, 0, 0, 0],
      [0, 0, 0, 0, 0],
      [0, 0, 0, 0, 0],
      [0, 0, 0, 0, 0],
      [0, 0, 0, 0, 0]
    ],
    [
      [0, 0, 0, 0, 0],
      [0, 0, 0, 0, 0],
      [0, 0, 0, 0, 0],
      [0, 0, 0, 0, 0],
      [0, 0, 0, 0, 0]
    ],
    [
      [0, 0, 0, 0, 0],
      [0, 0, 0, 0, 0],
      [0, 0, 0, 0, 0],
      [0, 0, 0, 0, 0],
      [0, 0, 0, 0, 0]
    ],
    [
      [0, 0, 0, 0, 0],
      [0, 0, 0, 0, 0],
      [0, 0, 0, 0, 0],
      [0, 0, 0, 0, 0],
      [0, 0, 0, 0, 0]
    ],
    [
      [0, 0, 0, 0, 0],
      [0, 0, 0, 0, 0],
      [0, 0, 0, 0, 0],
      [0, 0, 0, 0, 0],
      [0, 0, 0, 0, 0]
    ],
    [
      [0, 0, 0, 0, 0],
      [0, 0, 0, 0, 0],
      [0, 0, 0, 0, 0],
      [0, 0, 0, 0, 0],
      [0, 0, 0, 0, 0]
    ],
    [
      [0, 0, 0, 0, 0],
      [0, 0, 0, 0, 0],
      [0, 0, 0, 0, 0],
      [0, 0, 0, 0, 0],
      [0, 0, 0, 0, 0]
    ],
    [
      [0, 0, 0, 0, 0],
      [0, 0, 0, 0, 0],
      [0, 0, 0, 0, 0],
      [0, 0, 0, 0, 0],
      [0, 0, 0, 0, 0]
    ],
    [
      [0, 0, 0, 0, 0],
      [0, 0, 0, 0, 0],
      [0, 0, 0, 0, 0],
      [0, 0, 0, 0, 0],
      [0, 0, 0, 0, 0]
    ],
    [
      [0, 0, 0, 0, 0],
      [0, 0, 0, 0, 0],
      [0, 0, 0, 0, 0],
      [0, 0, 0, 0, 0],
      [0, 0, 0, 0, 0]
    ],
    [
      [0, 0, 0, 0, 0],
      [0, 0, 0, 0, 0],
      [0, 0, 0, 0, 0],
      [0, 0, 0, 0, 0],
      [0, 0, 0, 0, 0]
    ],
    [
      [0, 0, 0, 0, 0],
      [0, 0, 0, 0, 0],
      [0, 0, 0, 0, 0],
      [0, 0, 0, 0, 0],
      [0, 0, 0, 0, 0]
    ],
    [
      [0, 0, 0, 0, 0],
      [0, 0, 0, 0, 0],
      [0, 0, 0, 0, 0],
      [0, 0, 0, 0, 0],
      [0, 0, 0, 0, 0]
    ],
    [
      [0, 0, 0, 0, 0],
      [0, 0, 0, 0, 0],
      [0, 0, 0, 0, 0],
      [0, 0, 0, 0, 0],
      [0, 0, 0, 0, 0]
    ],
    [
      [0, 0, 0, 0, 0],
      [0, 0, 0, 0, 0],
      [0, 0, 0, 0, 0],
      [0, 0, 0, 0, 0],
      [0, 0, 0, 0, 0]
    ],
    [
      [0, 0, 0, 0, 0],
      [0, 0, 0, 0, 0],
      [0, 0, 0, 0, 0],
      [0, 0, 0, 0, 0],
      [0, 0, 0, 0, 0]
    ],
    [
      [0, 0, 0, 0, 0],
      [0, 0, 0, 0, 0],
      [0, 0, 0, 0, 0],
      [0, 0, 0, 0, 0],
      [0, 0, 0, 0, 0]
    ],
    [
      [0, 0, 0, 0, 0],
      [0, 0, 0, 0, 0],
      [0, 0, 0, 0, 0],
      [0, 0, 0, 0, 0],
      [0, 0, 0, 0, 0]
    ],
    [
      [0, 0, 0, 0, 0],
      [0, 0, 0, 0, 0],
      [0, 0, 0, 0, 0],
      [0, 0, 0, 0, 0],
      [0, 0, 0, 0, 0]
    ],
    [
      [0, 0, 0, 0, 0],
      [0, 0, 0, 0, 0],
      [0, 0, 0, 0, 0],
      [0, 0, 0, 0, 0],
      [0, 0, 0, 0, 0]
    ],
    [
      [0, 0, 0, 0, 0],
      [0, 0, 0, 0, 0],
      [0, 0, 0, 0, 0],
      [0, 0, 0, 0, 0],
      [0, 0, 0, 0, 0]
    ],
    [
      [0, 0, 0, 0, 0],
      [0, 0, 0, 0, 0],
      [0, 0, 0, 0, 0],
      [0, 0, 0, 0, 0],
      [0, 0, 0, 0, 0]
    ],
    [
      [0, 0, 0, 0, 0],
      [0, 0, 0, 0, 0],
      [0, 0, 0, 0, 0],
      [0, 0, 0, 0, 0],
      [0, 0, 0, 0, 0]
    ],
    [
      [0, 0, 0, 0, 0],
      [0, 0, 0, 0, 0],
      [0, 0, 0, 0, 0],
      [0, 0, 0, 0, 0],
      [0, 0, 0, 0, 0]
    ]
  ],
  "expected_outcome": [
    [
      [0, 0, 0, 0, 0, 0, 0, 0, 0, 0, 0, 0, 0, 0, 0, 0, 0, 0, 0, 0, 0, 0, 0, 0, 0, 0, 0, 0, 0, 0, 0, 0, 0, 0, 0, 0, 0, 0, 0, 0, 0, 0, 0, 0, 0, 0, 0, 0, 0, 0, 0, 0, 0, 0, 0, 0, 0, 0, 0],
      [0, 0, 0, 0, 0, 0, 0, 0, 0, 0, 0, 0, 0, 0, 0, 0, 0, 0, 0, 0, 0, 0, 0, 0, 0, 0, 0, 0, 0, 0, 0, 0, 0, 0, 0, 0, 0, 0, 0, 0, 0, 0, 0, 0, 0, 0, 0, 0, 0, 0, 0, 0, 0, 0, 0, 0, 0, 0, 0],
      [0, 0, 0, 0, 0, 0, 0, 0, 0, 0, 0, 0, 0, 0, 0, 0, 0, 0, 0, 0, 0, 0, 0, 0, 0, 0, 0, 0, 0, 0, 0, 0, 0, 0, 0, 0, 0, 0, 0, 0, 0, 0, 0, 0, 0, 0, 0, 0, 0, 0, 0, 0, 0, 0, 0, 0, 0, 0, 0],
      [0, 0, 0, 0, 0, 0, 0, 0, 0, 0, 0, 0, 0, 0, 0, 0, 0, 0, 0, 0, 0, 0, 0, 0, 0, 0, 0, 0, 0, 0, 0, 0, 0, 0, 0, 0, 0, 0, 0, 0, 0, 0, 0, 0, 0, 0, 0, 0, 0, 0, 0, 0, 0, 0, 0, 0, 0, 0, 0],
      [0, 0, 0, 0, 0, 0, 0, 0, 0, 0, 0, 0, 0, 0, 0, 0, 0, 0, 0, 0, 0, 0, 0, 0, 0, 0, 0, 0, 0, 0, 0, 0, 0, 0, 0, 0, 0, 0, 0, 0, 0, 0, 0, 0, 0, 0, 0, 0, 0, 0, 0, 0, 0, 0, 0, 0, 0, 0, 0]
    ],
    [
      [0, 0, 0, 0, 0, 0, 0, 0, 0, 0, 0, 0, 0, 0, 0, 0, 0, 0, 0, 0, 0, 0, 0, 0, 0, 0, 0, 0, 0, 0, 0, 0, 0, 0, 0, 0, 0, 0, 0, 0, 0, 0, 0, 0, 0, 0, 0, 0, 0, 0, 0, 0, 0, 0, 0, 0, 0, 0, 0],
      [0, 0, 0, 0, 0, 0, 0, 0, 0, 0, 0, 0, 0, 0, 0, 0, 0, 0, 0, 0, 0, 0, 0, 0, 0, 0, 0, 0, 0, 0, 0, 0, 0, 0, 0, 0, 0, 0, 0, 0, 0, 0, 0, 0, 0, 0, 0, 0, 0, 0, 0, 0, 0, 0, 0, 0, 0, 0, 0],
      [0, 0, 0, 0, 0, 0, 0, 0, 0, 0, 0, 0, 0, 0, 0, 0, 0, 0, 0, 0, 0, 0, 0, 0, 0, 0, 0, 0, 0, 0, 0, 0, 0, 0, 0, 0, 0, 0, 0, 0, 0, 0, 0, 0, 0, 0, 0, 0, 0, 0, 0, 0, 0, 0, 0, 0, 0, 0, 0],
      [0, 0, 0, 0, 0, 0, 0, 0, 0, 0, 0, 0, 0, 0, 0, 0, 0, 0, 0, 0, 0, 0, 0, 0, 0, 0, 0, 0, 0, 0, 0, 0, 0, 0, 0, 0, 0, 0, 0, 0, 0, 0, 0, 0, 0, 0, 0, 0, 0, 0, 0, 0, 0, 0, 0, 0, 0, 0, 0],
      [0, 0, 0, 0, 0, 0, 0, 0, 0, 0, 0, 0, 0, 0, 0, 0, 0, 0, 0, 0, 0, 0, 0, 0, 0, 0, 0, 0, 0, 0, 0, 0, 0, 0, 0, 0, 0, 0, 0, 0, 0, 0, 0, 0, 0, 0, 0, 0, 0, 0, 0, 0, 0, 0, 0, 0, 0, 0, 0]
    ],
    [
      [0, 0, 0, 0, 0, 0, 0, 0, 0, 0, 0, 0, 0, 0, 0, 0, 0, 0, 0, 0, 0, 0, 0, 0, 0, 0, 0, 0, 0, 0, 0, 0, 0, 0, 0, 0, 0, 0, 0, 0, 0, 0, 0, 0, 0, 0, 0, 0, 0, 0, 0, 0, 0, 0, 0, 0, 0, 0, 0],
      [0, 0, 0, 0, 0, 0, 0, 0, 0, 0, 0, 0, 0, 0, 0, 0, 0, 0, 0, 0, 0, 0, 0, 0, 0, 0, 0, 0, 0, 0, 0, 0, 0, 0, 0, 0, 0, 0, 0, 0, 0, 0, 0, 0, 0, 0, 0, 0, 0, 0, 0, 0, 0, 0, 0, 0, 0, 0, 0],
      [0, 0, 0, 0, 0, 0, 0, 0, 0, 0, 0, 0, 0, 0, 0, 0, 0, 0, 0, 0, 0, 0, 0, 0, 0, 0, 0, 0, 0, 0, 0, 0, 0, 0, 0, 0, 0, 0, 0, 0, 0, 0, 0, 0, 0, 0, 0, 0, 0, 0, 0, 0, 0, 0, 0, 0, 0, 0, 0],
      [0, 0, 0, 0, 0, 0, 0, 0, 0, 0, 0, 0, 0, 0, 0, 0, 0, 0, 0, 0, 0, 0, 0, 0, 0, 0, 0, 0, 0, 0, 0, 0, 0, 0, 0, 0, 0, 0, 0, 0, 0, 0, 0, 0, 0, 0, 0, 0, 0, 0, 0, 0, 0, 0, 0, 0, 0, 0, 0],
      [0, 0, 0, 0, 0, 0, 0, 0, 0, 0, 0, 0, 0, 0, 0, 0, 0, 0, 0, 0, 0, 0, 0, 0, 0, 0, 0, 0, 0, 0, 0, 0, 0, 0, 0, 0, 0, 0, 0, 0, 0, 0, 0, 0, 0, 0, 0, 0, 0, 0, 0, 0, 0, 0, 0, 0, 0, 0, 0]
    ],
    [
      [0, 0, 0, 0, 0, 0, 0, 0, 0, 0, 0, 0, 0, 0, 0, 0, 0, 0, 0, 0, 0, 0, 0, 0, 0, 0, 0, 0, 0, 0, 0, 0, 0, 0, 0, 0, 0, 0, 0, 0, 0, 0, 0, 0, 0, 0, 0, 0, 0, 0, 0, 0, 0, 0, 0, 0, 0, 0, 0],
      [0, 0, 0, 0, 0, 0, 0, 0, 0, 0, 0, 0, 0, 0, 0, 0, 0, 0, 0, 0, 0, 0, 0, 0, 0, 0, 0, 0, 0, 0, 0, 0, 0, 0, 0, 0, 0, 0, 0, 0, 0, 0, 0, 0, 0, 0, 0, 0, 0, 0, 0, 0, 0, 0, 0, 0, 0, 0, 0],
      [0, 0, 0, 0, 0, 0, 0, 0, 0, 0, 0, 0, 0, 0, 0, 0, 0, 0, 0, 0, 0, 0, 0, 0, 0, 0, 0, 0, 0, 0, 0, 0, 0, 0, 0, 0, 0, 0, 0, 0, 0, 0, 0, 0, 0, 0, 0, 0, 0, 0, 0, 0, 0, 0, 0, 0, 0, 0, 0],
      [0, 0, 0, 0, 0, 0, 0, 0, 0, 0, 0, 0, 0, 0, 0, 0, 0, 0, 0, 0, 0, 0, 0, 0, 0, 0, 0, 0, 0, 0, 0, 0, 0, 0, 0, 0, 0, 0, 0, 0, 0, 0, 0, 0, 0, 0, 0, 0, 0, 0, 0, 0, 0, 0, 0, 0, 0, 0, 0],
      [0, 0, 0, 0, 0, 0, 0, 0, 0, 0, 0, 0, 0, 0, 0, 0, 0, 0, 0, 0, 0, 0, 0, 0, 0, 0, 0, 0, 0, 0, 0, 0, 0, 0, 0, 0, 0, 0, 0, 0, 0, 0, 0, 0, 0, 0, 0, 0, 0, 0, 0, 0, 0, 0, 0, 0, 0, 0, 0]
    ],
    [
      [0, 0, 0, 0, 0, 0, 0, 0, 0, 0, 0, 0, 0, 0, 0, 0, 0, 0, 0, 0, 0, 0, 0, 0, 0, 0, 0, 0, 0, 0, 0, 0, 0, 0, 0, 0, 0, 0, 0, 0, 0, 0, 0, 0, 0, 0, 0, 0, 0, 0, 0, 0, 0, 0, 0, 0, 0, 0, 0],
      [0, 0, 0, 0, 0, 0, 0, 0, 0, 0, 0, 0, 0, 0, 0, 0, 0, 0, 0, 0, 0, 0, 0, 0, 0, 0, 0, 0, 0, 0, 0, 0, 0, 0, 0, 0, 0, 0, 0, 0, 0, 0, 0, 0, 0, 0, 0, 0, 0, 0, 0, 0, 0, 0, 0, 0, 0, 0, 0],
      [0, 0, 0, 0, 0, 0, 0, 0, 0, 0, 0, 0, 0, 0, 0, 0, 0, 0, 0, 0, 0, 0, 0, 0, 0, 0, 0, 0, 0, 0, 0, 0, 0, 0, 0, 0, 0, 0, 0, 0, 0, 0, 0, 0, 0, 0, 0, 0, 0, 0, 0, 0, 0, 0, 0, 0, 0, 0, 0],
      [0, 0, 0, 0, 0, 0, 0, 0, 0, 0, 0, 0, 0, 0, 0, 0, 0, 0, 0, 0, 0, 0, 0, 0, 0, 0, 0, 0, 0, 0, 0, 0, 0, 0, 0, 0, 0, 0, 0, 0, 0, 0, 0, 0, 0, 0, 0, 0, 0, 0, 0, 0, 0, 0, 0, 0, 0, 0, 0],
      [0, 0, 0, 0, 0, 0, 0, 0, 0, 0, 0, 0, 0, 0, 0, 0, 0, 0, 0, 0, 0, 0, 0, 0, 0, 0, 0, 0, 0, 0, 0, 0, 0, 0, 0, 0, 0, 0, 0, 0, 0, 0, 0, 0, 0, 0, 0, 0, 0, 0, 0, 0, 0, 0, 0, 0, 0, 0, 0]
    ]
  ],
  "prob": [
    [0, 0, 0, 0, 0],
    [0, 0, 0, 0, 0],
    [0, 0, 0, 0, 0],
    [0, 0, 0, 0, 0],
    [0, 0, 0, 0, 0]
  ],
  "iterations": 4,
  "time": 0.022536,
  "message": "Converged",
  "status": 0,
  "miniter": 0,
  "maxiter": 1000,
  "maxtime": 3600,
  "param_threshold": 0.001,
  "ll_threshold": "-Inf",
  "initial_prob": "group_proportional",
  "candidates_id": ["FOOTE, John Edward.c", "FITZSIMONS, Jeanette Mary.c", "PURNELL, Max Andrew.c", "GOUDIE, Sandra Anne.c", "Other candidates votes.c"],
  "group_id": ["Green Party.p", "Labour Party.p", "National Party.p", "New Zealand First Party.p", "Other parties votes.p"]
}
