{
  "X": [
    [0, 0, 4, 9, 0],
    [24, 44, 112, 457, 22],
    [9, 25, 72, 230, 10],
    [13, 19, 52, 274, 21],
    [21, 22, 154, 243, 22],
    [13, 29, 157, 198, 12],
    [2, 7, 19, 12, 4],
    [9, 28, 68, 206, 12],
    [33, 43, 214, 239, 22],
    [45, 113, 695, 511, 36],
    [19, 40, 252, 178, 17],
    [5, 7, 10, 6, 0],
    [4, 13, 23, 37, 3],
    [0, 6, 12, 23, 1],
    [0, 4, 6, 15, 1],
    [25, 70, 196, 273, 13],
    [21, 26, 98, 112, 9],
    [0, 9, 11, 17, 2],
    [7, 27, 62, 111, 8],
    [4, 13, 16, 24, 5],
    [21, 45, 106, 205, 23],
    [3, 8, 15, 41, 0],
    [15, 40, 179, 138, 8],
    [3, 10, 23, 26, 0],
    [2, 3, 18, 12, 1],
    [39, 42, 481, 164, 25],
    [39, 156, 298, 609, 44],
    [22, 85, 180, 373, 40],
    [33, 57, 182, 320, 20],
    [28, 115, 257, 514, 25],
    [9, 24, 176, 76, 6],
    [0, 1, 6, 2, 4],
    [82, 148, 652, 723, 49],
    [1, 3, 8, 16, 4],
    [59, 86, 643, 483, 40],
    [34, 87, 245, 324, 34],
    [20, 47, 99, 232, 20],
    [33, 118, 422, 432, 44],
    [21, 55, 175, 209, 15],
    [31, 165, 352, 591, 47],
    [14, 20, 70, 179, 13],
    [7, 13, 32, 124, 7],
    [370, 831, 3194, 4733, 321],
    [31, 114, 302, 422, 59],
    [91, 326, 691, 949, 141],
    [9, 62, 109, 149, 5]
  ],
  "W": [
    [0, 5, 3, 4, 1, 0],
    [20, 41, 335, 137, 103, 23],
    [10, 37, 153, 89, 45, 12],
    [13, 26, 220, 62, 38, 20],
    [16, 38, 175, 181, 44, 8],
    [15, 32, 117, 192, 42, 11],
    [1, 3, 12, 20, 6, 2],
    [12, 20, 161, 86, 33, 11],
    [29, 55, 148, 263, 43, 13],
    [39, 122, 319, 797, 100, 23],
    [20, 46, 106, 279, 39, 16],
    [1, 8, 4, 14, 1, 0],
    [2, 22, 16, 31, 7, 2],
    [0, 8, 13, 20, 1, 0],
    [0, 6, 12, 7, 0, 1],
    [23, 74, 175, 240, 51, 14],
    [12, 24, 67, 111, 43, 9],
    [0, 5, 21, 11, 1, 1],
    [3, 31, 71, 66, 32, 12],
    [2, 10, 21, 19, 8, 2],
    [15, 48, 147, 128, 46, 16],
    [2, 13, 24, 18, 4, 6],
    [14, 30, 103, 194, 28, 11],
    [1, 7, 19, 30, 5, 0],
    [1, 4, 9, 19, 1, 2],
    [25, 55, 98, 513, 51, 9],
    [32, 200, 402, 349, 123, 40],
    [24, 111, 237, 209, 81, 38],
    [18, 80, 214, 220, 64, 16],
    [26, 156, 319, 307, 96, 35],
    [7, 33, 39, 184, 19, 9],
    [1, 2, 3, 5, 1, 1],
    [59, 163, 462, 788, 147, 35],
    [2, 3, 13, 10, 4, 0],
    [32, 121, 300, 733, 98, 27],
    [27, 119, 221, 268, 64, 25],
    [22, 45, 183, 108, 40, 20],
    [31, 116, 310, 476, 80, 36],
    [17, 60, 158, 193, 36, 11],
    [27, 256, 345, 423, 107, 28],
    [16, 30, 102, 93, 42, 13],
    [5, 20, 94, 38, 21, 5],
    [324, 1153, 3157, 3627, 936, 252],
    [23, 134, 332, 314, 76, 49],
    [69, 356, 692, 789, 200, 92],
    [7, 111, 84, 116, 9, 7]
  ],
  "method": "mvn_cdf",
  "mvncdf_method": "genz",
  "mvncdf_samples": 5000,
  "mvncdf_error": 1e-06,
  "cond_prob": [
    [
      [0, 0, 0, 0, 0],
      [0, 0, 0, 0, 0],
      [0, 0, 0, 0, 0],
      [0, 0, 0, 0, 0],
      [0, 0, 0, 0, 0],
      [0, 0, 0, 0, 0]
    ],
    [
      [0, 0, 0, 0, 0],
      [0, 0, 0, 0, 0],
      [0, 0, 0, 0, 0],
      [0, 0, 0, 0, 0],
      [0, 0, 0, 0, 0],
      [0, 0, 0, 0, 0]
    ],
    [
      [0, 0, 0, 0, 0],
      [0, 0, 0, 0, 0],
      [0, 0, 0, 0, 0],
      [0, 0, 0, 0, 0],
      [0, 0, 0, 0, 0],
      [0, 0, 0, 0, 0]
    ],
    [
      [0, 0, 0, 0, 0],
      [0, 0, 0, 0, 0],
      [0, 0, 0, 0, 0],
      [0, 0, 0, 0, 0],
      [0, 0, 0, 0, 0],
      [0, 0, 0, 0, 0]
    ],
    [
      [0, 0, 0, 0, 0],
      [0, 0, 0, 0, 0],
      [0, 0, 0, 0, 0],
      [0, 0, 0, 0, 0],
      [0, 0, 0, 0, 0],
      [0, 0, 0, 0, 0]
    ],
    [
      [0, 0, 0, 0, 0],
      [0, 0, 0, 0, 0],
      [0, 0, 0, 0, 0],
      [0, 0, 0, 0, 0],
      [0, 0, 0, 0, 0],
      [0, 0, 0, 0, 0]
    ],
    [
      [0, 0, 0, 0, 0],
      [0, 0, 0, 0, 0],
      [0, 0, 0, 0, 0],
      [0, 0, 0, 0, 0],
      [0, 0, 0, 0, 0],
      [0, 0, 0, 0, 0]
    ],
    [
      [0, 0, 0, 0, 0],
      [0, 0, 0, 0, 0],
      [0, 0, 0, 0, 0],
      [0, 0, 0, 0, 0],
      [0, 0, 0, 0, 0],
      [0, 0, 0, 0, 0]
    ],
    [
      [0, 0, 0, 0, 0],
      [0, 0, 0, 0, 0],
      [0, 0, 0, 0, 0],
      [0, 0, 0, 0, 0],
      [0, 0, 0, 0, 0],
      [0, 0, 0, 0, 0]
    ],
    [
      [0, 0, 0, 0, 0],
      [0, 0, 0, 0, 0],
      [0, 0, 0, 0, 0],
      [0, 0, 0, 0, 0],
      [0, 0, 0, 0, 0],
      [0, 0, 0, 0, 0]
    ],
    [
      [0, 0, 0, 0, 0],
      [0, 0, 0, 0, 0],
      [0, 0, 0, 0, 0],
      [0, 0, 0, 0, 0],
      [0, 0, 0, 0, 0],
      [0, 0, 0, 0, 0]
    ],
    [
      [0, 0, 0, 0, 0],
      [0, 0, 0, 0, 0],
      [0, 0, 0, 0, 0],
      [0, 0, 0, 0, 0],
      [0, 0, 0, 0, 0],
      [0, 0, 0, 0, 0]
    ],
    [
      [0, 0, 0, 0, 0],
      [0, 0, 0, 0, 0],
      [0, 0, 0, 0, 0],
      [0, 0, 0, 0, 0],
      [0, 0, 0, 0, 0],
      [0, 0, 0, 0, 0]
    ],
    [
      [0, 0, 0, 0, 0],
      [0, 0, 0, 0, 0],
      [0, 0, 0, 0, 0],
      [0, 0, 0, 0, 0],
      [0, 0, 0, 0, 0],
      [0, 0, 0, 0, 0]
    ],
    [
      [0, 0, 0, 0, 0],
      [0, 0, 0, 0, 0],
      [0, 0, 0, 0, 0],
      [0, 0, 0, 0, 0],
      [0, 0, 0, 0, 0],
      [0, 0, 0, 0, 0]
    ],
    [
      [0, 0, 0, 0, 0],
      [0, 0, 0, 0, 0],
      [0, 0, 0, 0, 0],
      [0, 0, 0, 0, 0],
      [0, 0, 0, 0, 0],
      [0, 0, 0, 0, 0]
    ],
    [
      [0, 0, 0, 0, 0],
      [0, 0, 0, 0, 0],
      [0, 0, 0, 0, 0],
      [0, 0, 0, 0, 0],
      [0, 0, 0, 0, 0],
      [0, 0, 0, 0, 0]
    ],
    [
      [0, 0, 0, 0, 0],
      [0, 0, 0, 0, 0],
      [0, 0, 0, 0, 0],
      [0, 0, 0, 0, 0],
      [0, 0, 0, 0, 0],
      [0, 0, 0, 0, 0]
    ],
    [
      [0, 0, 0, 0, 0],
      [0, 0, 0, 0, 0],
      [0, 0, 0, 0, 0],
      [0, 0, 0, 0, 0],
      [0, 0, 0, 0, 0],
      [0, 0, 0, 0, 0]
    ],
    [
      [0, 0, 0, 0, 0],
      [0, 0, 0, 0, 0],
      [0, 0, 0, 0, 0],
      [0, 0, 0, 0, 0],
      [0, 0, 0, 0, 0],
      [0, 0, 0, 0, 0]
    ],
    [
      [0, 0, 0, 0, 0],
      [0, 0, 0, 0, 0],
      [0, 0, 0, 0, 0],
      [0, 0, 0, 0, 0],
      [0, 0, 0, 0, 0],
      [0, 0, 0, 0, 0]
    ],
    [
      [0, 0, 0, 0, 0],
      [0, 0, 0, 0, 0],
      [0, 0, 0, 0, 0],
      [0, 0, 0, 0, 0],
      [0, 0, 0, 0, 0],
      [0, 0, 0, 0, 0]
    ],
    [
      [0, 0, 0, 0, 0],
      [0, 0, 0, 0, 0],
      [0, 0, 0, 0, 0],
      [0, 0, 0, 0, 0],
      [0, 0, 0, 0, 0],
      [0, 0, 0, 0, 0]
    ],
    [
      [0, 0, 0, 0, 0],
      [0, 0, 0, 0, 0],
      [0, 0, 0, 0, 0],
      [0, 0, 0, 0, 0],
      [0, 0, 0, 0, 0],
      [0, 0, 0, 0, 0]
    ],
    [
      [0, 0, 0, 0, 0],
      [0, 0, 0, 0, 0],
      [0, 0, 0, 0, 0],
      [0, 0, 0, 0, 0],
      [0, 0, 0, 0, 0],
      [0, 0, 0, 0, 0]
    ],
    [
      [0, 0, 0, 0, 0],
      [0, 0, 0, 0, 0],
      [0, 0, 0, 0, 0],
      [0, 0, 0, 0, 0],
      [0, 0, 0, 0, 0],
      [0, 0, 0, 0, 0]
    ],
    [
      [0, 0, 0, 0, 0],
      [0, 0, 0, 0, 0],
      [0, 0, 0, 0, 0],
      [0, 0, 0, 0, 0],
      [0, 0, 0, 0, 0],
      [0, 0, 0, 0, 0]
    ],
    [
      [0, 0, 0, 0, 0],
      [0, 0, 0, 0, 0],
      [0, 0, 0, 0, 0],
      [0, 0, 0, 0, 0],
      [0, 0, 0, 0, 0],
      [0, 0, 0, 0, 0]
    ],
    [
      [0, 0, 0, 0, 0],
      [0, 0, 0, 0, 0],
      [0, 0, 0, 0, 0],
      [0, 0, 0, 0, 0],
      [0, 0, 0, 0, 0],
      [0, 0, 0, 0, 0]
    ],
    [
      [0, 0, 0, 0, 0],
      [0, 0, 0, 0, 0],
      [0, 0, 0, 0, 0],
      [0, 0, 0, 0, 0],
      [0, 0, 0, 0, 0],
      [0, 0, 0, 0, 0]
    ],
    [
      [0, 0, 0, 0, 0],
      [0, 0, 0, 0, 0],
      [0, 0, 0, 0, 0],
      [0, 0, 0, 0, 0],
      [0, 0, 0, 0, 0],
      [0, 0, 0, 0, 0]
    ],
    [
      [0, 0, 0, 0, 0],
      [0, 0, 0, 0, 0],
      [0, 0, 0, 0, 0],
      [0, 0, 0, 0, 0],
      [0, 0, 0, 0, 0],
      [0, 0, 0, 0, 0]
    ],
    [
      [0, 0, 0, 0, 0],
      [0, 0, 0, 0, 0],
      [0, 0, 0, 0, 0],
      [0, 0, 0, 0, 0],
      [0, 0, 0, 0, 0],
      [0, 0, 0, 0, 0]
    ],
    [
      [0, 0, 0, 0, 0],
      [0, 0, 0, 0, 0],
      [0, 0, 0, 0, 0],
      [0, 0, 0, 0, 0],
      [0, 0, 0, 0, 0],
      [0, 0, 0, 0, 0]
    ],
    [
      [0, 0, 0, 0, 0],
      [0, 0, 0, 0, 0],
      [0, 0, 0, 0, 0],
      [0, 0, 0, 0, 0],
      [0, 0, 0, 0, 0],
      [0, 0, 0, 0, 0]
    ],
    [
      [0, 0, 0, 0, 0],
      [0, 0, 0, 0, 0],
      [0, 0, 0, 0, 0],
      [0, 0, 0, 0, 0],
      [0, 0, 0, 0, 0],
      [0, 0, 0, 0, 0]
    ],
    [
      [0, 0, 0, 0, 0],
      [0, 0, 0, 0, 0],
      [0, 0, 0, 0, 0],
      [0, 0, 0, 0, 0],
      [0, 0, 0, 0, 0],
      [0, 0, 0, 0, 0]
    ],
    [
      [0, 0, 0, 0, 0],
      [0, 0, 0, 0, 0],
      [0, 0, 0, 0, 0],
      [0, 0, 0, 0, 0],
      [0, 0, 0, 0, 0],
      [0, 0, 0, 0, 0]
    ],
    [
      [0, 0, 0, 0, 0],
      [0, 0, 0, 0, 0],
      [0, 0, 0, 0, 0],
      [0, 0, 0, 0, 0],
      [0, 0, 0, 0, 0],
      [0, 0, 0, 0, 0]
    ],
    [
      [0, 0, 0, 0, 0],
      [0, 0, 0, 0, 0],
      [0, 0, 0, 0, 0],
      [0, 0, 0, 0, 0],
      [0, 0, 0, 0, 0],
      [0, 0, 0, 0, 0]
    ],
    [
      [0, 0, 0, 0, 0],
      [0, 0, 0, 0, 0],
      [0, 0, 0, 0, 0],
      [0, 0, 0, 0, 0],
      [0, 0, 0, 0, 0],
      [0, 0, 0, 0, 0]
    ],
    [
      [0, 0, 0, 0, 0],
      [0, 0, 0, 0, 0],
      [0, 0, 0, 0, 0],
      [0, 0, 0, 0, 0],
      [0, 0, 0, 0, 0],
      [0, 0, 0, 0, 0]
    ],
    [
      [0, 0, 0, 0, 0],
      [0, 0, 0, 0, 0],
      [0, 0, 0, 0, 0],
      [0, 0, 0, 0, 0],
      [0, 0, 0, 0, 0],
      [0, 0, 0, 0, 0]
    ],
    [
      [0, 0, 0, 0, 0],
      [0, 0, 0, 0, 0],
      [0, 0, 0, 0, 0],
      [0, 0, 0, 0, 0],
      [0, 0, 0, 0, 0],
      [0, 0, 0, 0, 0]
    ],
    [
      [0, 0, 0, 0, 0],
      [0, 0, 0, 0, 0],
      [0, 0, 0, 0, 0],
      [0, 0, 0, 0, 0],
      [0, 0, 0, 0, 0],
      [0, 0, 0, 0, 0]
    ],
    [
      [0, 0, 0, 0, 0],
      [0, 0, 0, 0, 0],
      [0, 0, 0, 0, 0],
      [0, 0, 0, 0, 0],
      [0, 0, 0, 0, 0],
      [0, 0, 0, 0, 0]
    ]
  ],
  "expected_outcome": [
    [
      [0, 0, 0, 0, 0, 0, 0, 0, 0, 0, 0, 0, 0, 0, 0, 0, 0, 0, 0, 0, 0, 0, 0, 0, 0, 0, 0, 0, 0, 0, 0, 0, 0, 0, 0, 0, 0, 0, 0, 0, 0, 0, 0, 0, 0, 0],
      [0, 0, 0, 0, 0, 0, 0, 0, 0, 0, 0, 0, 0, 0, 0, 0, 0, 0, 0, 0, 0, 0, 0, 0, 0, 0, 0, 0, 0, 0, 0, 0, 0, 0, 0, 0, 0, 0, 0, 0, 0, 0, 0, 0, 0, 0],
      [0, 0, 0, 0, 0, 0, 0, 0, 0, 0, 0, 0, 0, 0, 0, 0, 0, 0, 0, 0, 0, 0, 0, 0, 0, 0, 0, 0, 0, 0, 0, 0, 0, 0, 0, 0, 0, 0, 0, 0, 0, 0, 0, 0, 0, 0],
      [0, 0, 0, 0, 0, 0, 0, 0, 0, 0, 0, 0, 0, 0, 0, 0, 0, 0, 0, 0, 0, 0, 0, 0, 0, 0, 0, 0, 0, 0, 0, 0, 0, 0, 0, 0, 0, 0, 0, 0, 0, 0, 0, 0, 0, 0],
      [0, 0, 0, 0, 0, 0, 0, 0, 0, 0, 0, 0, 0, 0, 0, 0, 0, 0, 0, 0, 0, 0, 0, 0, 0, 0, 0, 0, 0, 0, 0, 0, 0, 0, 0, 0, 0, 0, 0, 0, 0, 0, 0, 0, 0, 0]
    ],
    [
      [0, 0, 0, 0, 0, 0, 0, 0, 0, 0, 0, 0, 0, 0, 0, 0, 0, 0, 0, 0, 0, 0, 0, 0, 0, 0, 0, 0, 0, 0, 0, 0, 0, 0, 0, 0, 0, 0, 0, 0, 0, 0, 0, 0, 0, 0],
      [0, 0, 0, 0, 0, 0, 0, 0, 0, 0, 0, 0, 0, 0, 0, 0, 0, 0, 0, 0, 0, 0, 0, 0, 0, 0, 0, 0, 0, 0, 0, 0, 0, 0, 0, 0, 0, 0, 0, 0, 0, 0, 0, 0, 0, 0],
      [0, 0, 0, 0, 0, 0, 0, 0, 0, 0, 0, 0, 0, 0, 0, 0, 0, 0, 0, 0, 0, 0, 0, 0, 0, 0, 0, 0, 0, 0, 0, 0, 0, 0, 0, 0, 0, 0, 0, 0, 0, 0, 0, 0, 0, 0],
      [0, 0, 0, 0, 0, 0, 0, 0, 0, 0, 0, 0, 0, 0, 0, 0, 0, 0, 0, 0, 0, 0, 0, 0, 0, 0, 0, 0, 0, 0, 0, 0, 0, 0, 0, 0, 0, 0, 0, 0, 0, 0, 0, 0, 0, 0],
      [0, 0, 0, 0, 0, 0, 0, 0, 0, 0, 0, 0, 0, 0, 0, 0, 0, 0, 0, 0, 0, 0, 0, 0, 0, 0, 0, 0, 0, 0, 0, 0, 0, 0, 0, 0, 0, 0, 0, 0, 0, 0, 0, 0, 0, 0]
    ],
    [
      [0, 0, 0, 0, 0, 0, 0, 0, 0, 0, 0, 0, 0, 0, 0, 0, 0, 0, 0, 0, 0, 0, 0, 0, 0, 0, 0, 0, 0, 0, 0, 0, 0, 0, 0, 0, 0, 0, 0, 0, 0, 0, 0, 0, 0, 0],
      [0, 0, 0, 0, 0, 0, 0, 0, 0, 0, 0, 0, 0, 0, 0, 0, 0, 0, 0, 0, 0, 0, 0, 0, 0, 0, 0, 0, 0, 0, 0, 0, 0, 0, 0, 0, 0, 0, 0, 0, 0, 0, 0, 0, 0, 0],
      [0, 0, 0, 0, 0, 0, 0, 0, 0, 0, 0, 0, 0, 0, 0, 0, 0, 0, 0, 0, 0, 0, 0, 0, 0, 0, 0, 0, 0, 0, 0, 0, 0, 0, 0, 0, 0, 0, 0, 0, 0, 0, 0, 0, 0, 0],
      [0, 0, 0, 0, 0, 0, 0, 0, 0, 0, 0, 0, 0, 0, 0, 0, 0, 0, 0, 0, 0, 0, 0, 0, 0, 0, 0, 0, 0, 0, 0, 0, 0, 0, 0, 0, 0, 0, 0, 0, 0, 0, 0, 0, 0, 0],
      [0, 0, 0, 0, 0, 0, 0, 0, 0, 0, 0, 0, 0, 0, 0, 0, 0, 0, 0, 0, 0, 0, 0, 0, 0, 0, 0, 0, 0, 0, 0, 0, 0, 0, 0, 0, 0, 0, 0, 0, 0, 0, 0, 0, 0, 0]
    ],
    [
      [0, 0, 0, 0, 0, 0, 0, 0, 0, 0, 0, 0, 0, 0, 0, 0, 0, 0, 0, 0, 0, 0, 0, 0, 0, 0, 0, 0, 0, 0, 0, 0, 0, 0, 0, 0, 0, 0, 0, 0, 0, 0, 0, 0, 0, 0],
      [0, 0, 0, 0, 0, 0, 0, 0, 0, 0, 0, 0, 0, 0, 0, 0, 0, 0, 0, 0, 0, 0, 0, 0, 0, 0, 0, 0, 0, 0, 0, 0, 0, 0, 0, 0, 0, 0, 0, 0, 0, 0, 0, 0, 0, 0],
      [0, 0, 0, 0, 0, 0, 0, 0, 0, 0, 0, 0, 0, 0, 0, 0, 0, 0, 0, 0, 0, 0, 0, 0, 0, 0, 0, 0, 0, 0, 0, 0, 0, 0, 0, 0, 0, 0, 0, 0, 0, 0, 0, 0, 0, 0],
      [0, 0, 0, 0, 0, 0, 0, 0, 0, 0, 0, 0, 0, 0, 0, 0, 0, 0, 0, 0, 0, 0, 0, 0, 0, 0, 0, 0, 0, 0, 0, 0, 0, 0, 0, 0, 0, 0, 0, 0, 0, 0, 0, 0, 0, 0],
      [0, 0, 0, 0, 0, 0, 0, 0, 0, 0, 0, 0, 0, 0, 0, 0, 0, 0, 0, 0, 0, 0, 0, 0, 0, 0, 0, 0, 0, 0, 0, 0, 0, 0, 0, 0, 0, 0, 0, 0, 0, 0, 0, 0, 0, 0]
    ],
    [
      [0, 0, 0, 0, 0, 0, 0, 0, 0, 0, 0, 0, 0, 0, 0, 0, 0, 0, 0, 0, 0, 0, 0, 0, 0, 0, 0, 0, 0, 0, 0, 0, 0, 0, 0, 0, 0, 0, 0, 0, 0, 0, 0, 0, 0, 0],
      [0, 0, 0, 0, 0, 0, 0, 0, 0, 0, 0, 0, 0, 0, 0, 0, 0, 0, 0, 0, 0, 0, 0, 0, 0, 0, 0, 0, 0, 0, 0, 0, 0, 0, 0, 0, 0, 0, 0, 0, 0, 0, 0, 0, 0, 0],
      [0, 0, 0, 0, 0, 0, 0, 0, 0, 0, 0, 0, 0, 0, 0, 0, 0, 0, 0, 0, 0, 0, 0, 0, 0, 0, 0, 0, 0, 0, 0, 0, 0, 0, 0, 0, 0, 0, 0, 0, 0, 0, 0, 0, 0, 0],
      [0, 0, 0, 0, 0, 0, 0, 0, 0, 0, 0, 0, 0, 0, 0, 0, 0, 0, 0, 0, 0, 0, 0, 0, 0, 0, 0, 0, 0, 0, 0, 0, 0, 0, 0, 0, 0, 0, 0, 0, 0, 0, 0, 0, 0, 0],
      [0, 0, 0, 0, 0, 0, 0, 0, 0, 0, 0, 0, 0, 0, 0, 0, 0, 0, 0, 0, 0, 0, 0, 0, 0, 0, 0, 0, 0, 0, 0, 0, 0, 0, 0, 0, 0, 0, 0, 0, 0, 0, 0, 0, 0, 0]
    ],
    [
      [0, 0, 0, 0, 0, 0, 0, 0, 0, 0, 0, 0, 0, 0, 0, 0, 0, 0, 0, 0, 0, 0, 0, 0, 0, 0, 0, 0, 0, 0, 0, 0, 0, 0, 0, 0, 0, 0, 0, 0, 0, 0, 0, 0, 0, 0],
      [0, 0, 0, 0, 0, 0, 0, 0, 0, 0, 0, 0, 0, 0, 0, 0, 0, 0, 0, 0, 0, 0, 0, 0, 0, 0, 0, 0, 0, 0, 0, 0, 0, 0, 0, 0, 0, 0, 0, 0, 0, 0, 0, 0, 0, 0],
      [0, 0, 0, 0, 0, 0, 0, 0, 0, 0, 0, 0, 0, 0, 0, 0, 0, 0, 0, 0, 0, 0, 0, 0, 0, 0, 0, 0, 0, 0, 0, 0, 0, 0, 0, 0, 0, 0, 0, 0, 0, 0, 0, 0, 0, 0],
      [0, 0, 0, 0, 0, 0, 0, 0, 0, 0, 0, 0, 0, 0, 0, 0, 0, 0, 0, 0, 0, 0, 0, 0, 0, 0, 0, 0, 0, 0, 0, 0, 0, 0, 0, 0, 0, 0, 0, 0, 0, 0, 0, 0, 0, 0],
      [0, 0, 0, 0, 0, 0, 0, 0, 0, 0, 0, 0, 0, 0, 0, 0, 0, 0, 0, 0, 0, 0, 0, 0, 0, 0, 0, 0, 0, 0, 0, 0, 0, 0, 0, 0, 0, 0, 0, 0, 0, 0, 0, 0, 0, 0]
    ]
  ],
  "prob": [
    [0, 0, 0, 0, 0],
    [0, 0, 0, 0, 0],
    [0, 0, 0, 0, 0],
    [0, 0, 0, 0, 0],
    [0, 0, 0, 0, 0],
    [0, 0, 0, 0, 0]
  ],
  "iterations": 4,
  "time": 0.394987,
  "message": "Converged",
  "status": 0,
  "miniter": 0,
  "maxiter": 1000,
  "maxtime": 3600,
  "param_threshold": 0.001,
  "ll_threshold": "-Inf",
  "initial_prob": "group_proportional",
  "candidates_id": ["BAKER, Leighton James.c", "MATHERS, Mojo Celeste.c", "HAYES, Joanne Kowhai.c", "WILLIAMS, Munokoa Poto.c", "Other candidates votes.c"],
  "group_id": ["Conservative.p", "Green Party.p", "Labour Party.p", "National Party.p", "New Zealand First Party.p", "Other parties votes.p"]
}
